[{"id":4276,"code":"76193","name":"ADAM","medium":"R","uat_id":1335},{"id":4224,"code":"75374","name":"ALDE\u015eTI","medium":"R","uat_id":1317},{"id":4234,"code":"75551","name":"B\u0102L\u0102B\u0102NE\u015eTI","medium":"R","uat_id":1320},{"id":4237,"code":"75622","name":"B\u0102L\u0102\u015eE\u015eTI","medium":"R","uat_id":1321},{"id":4241,"code":"75677","name":"B\u0102LENI","medium":"R","uat_id":1322},{"id":4225,"code":"75383","name":"BALINTE\u015eTI","medium":"R","uat_id":1317},{"id":4268,"code":"76068","name":"B\u0102LT\u0102RE\u0162I","medium":"R","uat_id":1331},{"id":4242,"code":"75695","name":"B\u0102NEASA","medium":"R","uat_id":1323},{"id":4232,"code":"75524","name":"BARCEA","medium":"R","uat_id":1319},{"id":4222,"code":"75347","name":"BERE\u015eTI","medium":"U","uat_id":1316},{"id":4223,"code":"75365","name":"BERE\u015eTI-MERIA","medium":"R","uat_id":1317},{"id":4261,"code":"75971","name":"BL\u00c2NZI","medium":"R","uat_id":1329},{"id":4247,"code":"75775","name":"BR\u0102H\u0102\u015eE\u015eTI","medium":"R","uat_id":1325},{"id":4360,"code":"77554","name":"BR\u0102NE\u015eTI","medium":"R","uat_id":1369},{"id":4244,"code":"75720","name":"BRANI\u015eTEA","medium":"R","uat_id":1324},{"id":4262,"code":"75980","name":"BR\u0102TULE\u015eTI","medium":"R","uat_id":1329},{"id":4305,"code":"76629","name":"BUCE\u015eTI","medium":"R","uat_id":1344},{"id":4249,"code":"75828","name":"BUCIUMENI","medium":"R","uat_id":1326},{"id":4235,"code":"75560","name":"BURSUCANI","medium":"R","uat_id":1320},{"id":4302,"code":"76576","name":"C\u0102LM\u0102\u0162UI","medium":"R","uat_id":1342},{"id":4263,"code":"75999","name":"C\u0102R\u0102PCE\u015eTI","medium":"R","uat_id":1329},{"id":4258,"code":"75935","name":"C\u00c2RLOM\u0102NE\u015eTI","medium":"R","uat_id":1328},{"id":4277,"code":"76200","name":"C\u0102UIE\u015eTI","medium":"R","uat_id":1335},{"id":4253,"code":"75873","name":"CAVADINE\u015eTI","medium":"R","uat_id":1327},{"id":4257,"code":"75926","name":"CER\u0162E\u015eTI","medium":"R","uat_id":1328},{"id":4312,"code":"76736","name":"CHIRAFTEI","medium":"R","uat_id":1348},{"id":4328,"code":"77046","name":"CIOR\u0102\u015eTI","medium":"R","uat_id":1355},{"id":4339,"code":"77242","name":"CI\u015eMELE","medium":"R","uat_id":1360},{"id":4238,"code":"75631","name":"CIURE\u015eTI","medium":"R","uat_id":1321},{"id":4239,"code":"75640","name":"CIURE\u015eTII NOI","medium":"R","uat_id":1321},{"id":4317,"code":"76834","name":"COASTA LUPEI","medium":"R","uat_id":1351},{"id":4254,"code":"75882","name":"COM\u0102NE\u015eTI","medium":"R","uat_id":1327},{"id":4350,"code":"77420","name":"CONDREA","medium":"R","uat_id":1366},{"id":4264,"code":"76013","name":"CORNI","medium":"R","uat_id":1330},{"id":4260,"code":"75962","name":"COROD","medium":"R","uat_id":1329},{"id":4267,"code":"76059","name":"COSME\u015eTI","medium":"R","uat_id":1331},{"id":4269,"code":"76077","name":"COSME\u015eTII-VALE","medium":"R","uat_id":1331},{"id":4272,"code":"76120","name":"COSTACHE NEGRI","medium":"R","uat_id":1332},{"id":4213,"code":"75178","name":"COSTI","medium":"R","uat_id":1312},{"id":4259,"code":"75944","name":"COTOROAIA","medium":"R","uat_id":1328},{"id":4358,"code":"77527","name":"CR\u0102IE\u015eTI","medium":"R","uat_id":1368},{"id":4361,"code":"75579","name":"CRUCEANU","medium":"R","uat_id":1370},{"id":4273,"code":"76148","name":"CUCA","medium":"R","uat_id":1333},{"id":4274,"code":"76166","name":"CUDALBI","medium":"R","uat_id":1334},{"id":4367,"code":"77206","name":"CUZA VOD\u0102","medium":"R","uat_id":1373},{"id":4318,"code":"76843","name":"DOBRINE\u015eTI","medium":"R","uat_id":1351},{"id":4216,"code":"75230","name":"DR\u0102G\u0102NE\u015eTI","medium":"R","uat_id":1314},{"id":4275,"code":"76184","name":"DR\u0102GU\u015eENI","medium":"R","uat_id":1335},{"id":4333,"code":"77144","name":"F\u00c2NT\u00c2NELE","medium":"R","uat_id":1357},{"id":4319,"code":"76852","name":"F\u00c2NT\u00c2NI","medium":"R","uat_id":1351},{"id":4282,"code":"76264","name":"F\u00c2R\u0162\u0102NE\u015eTI","medium":"R","uat_id":1336},{"id":4284,"code":"76291","name":"FOLTE\u015eTI","medium":"R","uat_id":1337},{"id":4286,"code":"76326","name":"FRUMU\u015eI\u0162A","medium":"R","uat_id":1338},{"id":4219,"code":"75276","name":"FRUNZEASCA","medium":"R","uat_id":1315},{"id":4278,"code":"76219","name":"FUNDEANU","medium":"R","uat_id":1335},{"id":4289,"code":"76371","name":"FUNDENI","medium":"R","uat_id":1339},{"id":4270,"code":"76086","name":"FURCENII NOI","medium":"R","uat_id":1331},{"id":4271,"code":"76095","name":"FURCENII VECHI","medium":"R","uat_id":1331},{"id":4208,"code":"75105","name":"GALA\u0162I","medium":"U","uat_id":1310},{"id":4255,"code":"75891","name":"G\u0102NE\u015eTI","medium":"R","uat_id":1327},{"id":4298,"code":"76512","name":"GARA BERHECI","medium":"R","uat_id":1341},{"id":4294,"code":"76442","name":"G\u00c2RBOV\u0102\u0162","medium":"R","uat_id":1340},{"id":4293,"code":"76433","name":"GEFU","medium":"R","uat_id":1340},{"id":4292,"code":"76415","name":"GHIDIGENI","medium":"R","uat_id":1340},{"id":4279,"code":"76228","name":"GHINGHE\u015eTI","medium":"R","uat_id":1335},{"id":4297,"code":"76503","name":"GOHOR","medium":"R","uat_id":1341},{"id":4301,"code":"76567","name":"GRIVI\u0162A","medium":"R","uat_id":1342},{"id":4250,"code":"75837","name":"H\u0102N\u0162E\u015eTI","medium":"R","uat_id":1326},{"id":4290,"code":"76380","name":"HANU CONACHI","medium":"R","uat_id":1339},{"id":4287,"code":"76335","name":"IJDILENI","medium":"R","uat_id":1338},{"id":4303,"code":"76594","name":"INDEPENDEN\u0162A","medium":"R","uat_id":1343},{"id":4320,"code":"76870","name":"ION\u0102\u015eE\u015eTI","medium":"R","uat_id":1351},{"id":4304,"code":"76610","name":"IVE\u015eTI","medium":"R","uat_id":1344},{"id":4337,"code":"77215","name":"IZVOARELE","medium":"R","uat_id":1359},{"id":4306,"code":"76647","name":"JOR\u0102\u015eTI","medium":"R","uat_id":1345},{"id":4309,"code":"76683","name":"LIE\u015eTI","medium":"R","uat_id":1346},{"id":4329,"code":"77064","name":"LIE\u015eTI","medium":"R","uat_id":1355},{"id":4307,"code":"76656","name":"LUNCA","medium":"R","uat_id":1345},{"id":4236,"code":"75588","name":"LUNGE\u015eTI","medium":"R","uat_id":1320},{"id":4291,"code":"76399","name":"LUNGOCI","medium":"R","uat_id":1339},{"id":4265,"code":"76022","name":"M\u0102CI\u015eENI","medium":"R","uat_id":1330},{"id":4217,"code":"75249","name":"MALU ALB","medium":"R","uat_id":1314},{"id":4321,"code":"76889","name":"M\u0102LURENI","medium":"R","uat_id":1351},{"id":4356,"code":"77493","name":"M\u00c2NDRE\u015eTI","medium":"R","uat_id":1367},{"id":4311,"code":"76727","name":"M\u0102ST\u0102CANI","medium":"R","uat_id":1348},{"id":4310,"code":"76709","name":"MATCA","medium":"R","uat_id":1347},{"id":4340,"code":"77251","name":"MIHAIL KOG\u0102LNICEANU","medium":"R","uat_id":1360},{"id":4230,"code":"75490","name":"MOSCU","medium":"U","uat_id":1318},{"id":4313,"code":"76754","name":"MOVILENI","medium":"R","uat_id":1349},{"id":4210,"code":"75132","name":"MOVILENI","medium":"R","uat_id":1311},{"id":4218,"code":"75267","name":"MUNTENI","medium":"R","uat_id":1315},{"id":4314,"code":"76772","name":"N\u0102MOLOASA","medium":"R","uat_id":1350},{"id":4315,"code":"76790","name":"N\u0102MOLOASA-SAT","medium":"R","uat_id":1350},{"id":4300,"code":"76530","name":"N\u0102RTE\u015eTI","medium":"R","uat_id":1341},{"id":4335,"code":"77171","name":"NEGREA","medium":"R","uat_id":1358},{"id":4363,"code":"75285","name":"NEGRILE\u015eTI","medium":"R","uat_id":1371},{"id":4280,"code":"76237","name":"NICOPOLE","medium":"R","uat_id":1335},{"id":4316,"code":"76816","name":"NICORE\u015eTI","medium":"R","uat_id":1351},{"id":4323,"code":"76941","name":"OANCEA","medium":"R","uat_id":1352},{"id":4214,"code":"75187","name":"ODAIA MANOLACHE","medium":"R","uat_id":1312},{"id":4324,"code":"76978","name":"PECHEA","medium":"R","uat_id":1353},{"id":4325,"code":"77000","name":"PISCU","medium":"R","uat_id":1354},{"id":4322,"code":"76898","name":"PISCU CORBULUI","medium":"R","uat_id":1351},{"id":4226,"code":"75409","name":"PLE\u015eA","medium":"R","uat_id":1317},{"id":4331,"code":"77108","name":"PLEVNA","medium":"R","uat_id":1356},{"id":4233,"code":"75533","name":"PODOLENI","medium":"R","uat_id":1319},{"id":4365,"code":"76905","name":"POIANA","medium":"R","uat_id":1372},{"id":4327,"code":"77037","name":"PRIPONE\u015eTI","medium":"R","uat_id":1355},{"id":4240,"code":"75659","name":"PUPEZENI","medium":"R","uat_id":1321},{"id":4227,"code":"75427","name":"PURICANI","medium":"R","uat_id":1317},{"id":4362,"code":"75597","name":"R\u0102DE\u015eTI","medium":"R","uat_id":1370},{"id":4330,"code":"77091","name":"REDIU","medium":"R","uat_id":1356},{"id":4343,"code":"77304","name":"ROGOJENI","medium":"R","uat_id":1362},{"id":4243,"code":"75702","name":"RO\u015eCANI","medium":"R","uat_id":1323},{"id":4351,"code":"77439","name":"SALCIA","medium":"R","uat_id":1366},{"id":4332,"code":"77135","name":"SC\u00c2NTEIE\u015eTI","medium":"R","uat_id":1357},{"id":4334,"code":"77162","name":"SCHELA","medium":"R","uat_id":1358},{"id":4209,"code":"75123","name":"\u015eENDRENI","medium":"R","uat_id":1311},{"id":4211,"code":"75141","name":"\u015eERBE\u015eTII VECHI","medium":"R","uat_id":1311},{"id":4352,"code":"77448","name":"SILI\u015eTEA","medium":"R","uat_id":1366},{"id":4346,"code":"77359","name":"\u015eIVI\u0162A","medium":"R","uat_id":1364},{"id":4228,"code":"75445","name":"SLIVNA","medium":"R","uat_id":1317},{"id":4364,"code":"75294","name":"SLOBOZIA BL\u0102NEASA","medium":"R","uat_id":1371},{"id":4336,"code":"77199","name":"SLOBOZIA CONACHI","medium":"R","uat_id":1359},{"id":4295,"code":"76460","name":"SLOBOZIA CORNI","medium":"R","uat_id":1340},{"id":4338,"code":"77233","name":"SM\u00c2RDAN","medium":"R","uat_id":1360},{"id":4341,"code":"77279","name":"SMUL\u0162I","medium":"R","uat_id":1361},{"id":4281,"code":"76246","name":"\u015eTIE\u0162E\u015eTI","medium":"R","uat_id":1335},{"id":4285,"code":"76308","name":"STOICANI","medium":"R","uat_id":1337},{"id":4342,"code":"77297","name":"SUCEVENI","medium":"R","uat_id":1362},{"id":4368,"code":"77117","name":"SUHURLUI","medium":"R","uat_id":1374},{"id":4296,"code":"76479","name":"T\u0102LPIGI","medium":"R","uat_id":1340},{"id":4288,"code":"76344","name":"T\u0102M\u0102OANI","medium":"R","uat_id":1338},{"id":4229,"code":"75481","name":"T\u00c2RGU BUJOR","medium":"U","uat_id":1318},{"id":4347,"code":"77368","name":"T\u0102TARCA","medium":"R","uat_id":1364},{"id":4251,"code":"75846","name":"TECUCELU SEC","medium":"R","uat_id":1326},{"id":4215,"code":"75212","name":"TECUCI","medium":"U","uat_id":1313},{"id":4348,"code":"77386","name":"\u0162EPU","medium":"R","uat_id":1365},{"id":4220,"code":"75301","name":"\u0162IG\u0102NE\u015eTI","medium":"R","uat_id":1315},{"id":4248,"code":"75800","name":"TOFLEA","medium":"R","uat_id":1325},{"id":4353,"code":"77457","name":"TORCE\u015eTI","medium":"R","uat_id":1366},{"id":4245,"code":"75748","name":"TRAIAN","medium":"R","uat_id":1324},{"id":4344,"code":"77322","name":"TUDOR VLADIMIRESCU","medium":"R","uat_id":1363},{"id":4345,"code":"77340","name":"TULUCE\u015eTI","medium":"R","uat_id":1364},{"id":4231,"code":"75506","name":"UMBR\u0102RE\u015eTI","medium":"U","uat_id":1318},{"id":4349,"code":"77411","name":"UMBR\u0102RE\u015eTI","medium":"R","uat_id":1366},{"id":4354,"code":"77466","name":"UMBR\u0102RE\u015eTI-DEAL","medium":"R","uat_id":1366},{"id":4221,"code":"75310","name":"UNGURENI","medium":"R","uat_id":1315},{"id":4266,"code":"76031","name":"URLE\u015eTI","medium":"R","uat_id":1330},{"id":4256,"code":"75908","name":"V\u0102DENI","medium":"R","uat_id":1327},{"id":4355,"code":"77484","name":"VALEA M\u0102RULUI","medium":"R","uat_id":1367},{"id":4326,"code":"77019","name":"VAME\u015e","medium":"R","uat_id":1354},{"id":4212,"code":"75169","name":"V\u00c2N\u0102TORI","medium":"R","uat_id":1312},{"id":4357,"code":"77518","name":"V\u00c2RLEZI","medium":"R","uat_id":1368},{"id":4246,"code":"75757","name":"VASILE ALECSANDRI","medium":"R","uat_id":1324},{"id":4283,"code":"76273","name":"VIILE","medium":"R","uat_id":1336},{"id":4366,"code":"76923","name":"VI\u015eINA","medium":"R","uat_id":1372},{"id":4252,"code":"75855","name":"VIZURE\u015eTI","medium":"R","uat_id":1326},{"id":4359,"code":"77545","name":"VL\u0102DE\u015eTI","medium":"R","uat_id":1369},{"id":4308,"code":"76665","name":"Z\u0102RNE\u015eTI","medium":"R","uat_id":1345}]