[{"id":457,"name":"BISTRI\u0162A B\u00c2RG\u0102ULUI","code":"5","siruta":"32633","county_id":6},{"id":458,"name":"BRANI\u015eTEA","code":"6","siruta":"32660","county_id":6},{"id":459,"name":"BUDACU DE JOS","code":"7","siruta":"32704","county_id":6},{"id":460,"name":"BUDE\u015eTI","code":"8","siruta":"32768","county_id":6},{"id":461,"name":"C\u0102IANU MIC","code":"9","siruta":"32811","county_id":6},{"id":462,"name":"CETATE","code":"10","siruta":"32884","county_id":6},{"id":464,"name":"CHIOCHI\u015e","code":"11","siruta":"33015","county_id":6},{"id":465,"name":"CHIUZA","code":"12","siruta":"33122","county_id":6},{"id":463,"name":"CICEU-GIURGE\u015eTI","code":"13","siruta":"32955","county_id":6},{"id":514,"name":"CICEU-MIH\u0102IE\u015eTI","code":"14","siruta":"179953","county_id":6},{"id":466,"name":"CO\u015eBUC","code":"15","siruta":"33177","county_id":6},{"id":467,"name":"DUMITRA","code":"16","siruta":"33202","county_id":6},{"id":511,"name":"DUMITRI\u0162A","code":"17","siruta":"179686","county_id":6},{"id":468,"name":"FELDRU","code":"18","siruta":"33248","county_id":6},{"id":469,"name":"GALA\u0162II BISTRI\u0162EI","code":"19","siruta":"33275","county_id":6},{"id":470,"name":"ILVA MARE","code":"20","siruta":"33337","county_id":6},{"id":471,"name":"ILVA MIC\u0102","code":"21","siruta":"33364","county_id":6},{"id":472,"name":"JOSENII B\u00c2RG\u0102ULUI","code":"22","siruta":"33382","county_id":6},{"id":473,"name":"LECHIN\u0162A","code":"23","siruta":"33435","county_id":6},{"id":474,"name":"LE\u015eU","code":"24","siruta":"33514","county_id":6},{"id":475,"name":"LIVEZILE","code":"25","siruta":"33541","county_id":6},{"id":476,"name":"LUNCA ILVEI","code":"26","siruta":"33603","county_id":6},{"id":479,"name":"M\u0102GURA ILVEI","code":"29","siruta":"33729","county_id":6},{"id":477,"name":"MAIERU","code":"27","siruta":"33621","county_id":6},{"id":480,"name":"M\u0102RI\u015eELU","code":"30","siruta":"33765","county_id":6},{"id":478,"name":"MATEI","code":"28","siruta":"33658","county_id":6},{"id":481,"name":"MICE\u015eTII DE C\u00c2MPIE","code":"31","siruta":"33845","county_id":6},{"id":482,"name":"MILA\u015e","code":"32","siruta":"33881","county_id":6},{"id":483,"name":"MONOR","code":"33","siruta":"33952","county_id":6},{"id":453,"name":"MUNICIPIUL BISTRI\u0162A","code":"1","siruta":"32394","county_id":6},{"id":510,"name":"NEGRILE\u015eTI","code":"34","siruta":"179659","county_id":6},{"id":484,"name":"NIMIGEA","code":"35","siruta":"33989","county_id":6},{"id":485,"name":"NU\u015eENI","code":"36","siruta":"34075","county_id":6},{"id":454,"name":"ORA\u015e BECLEAN","code":"2","siruta":"32483","county_id":6},{"id":455,"name":"ORA\u015e N\u0102S\u0102UD","code":"3","siruta":"32544","county_id":6},{"id":456,"name":"ORA\u015e S\u00c2NGEORZ-B\u0102I","code":"4","siruta":"32599","county_id":6},{"id":486,"name":"PARVA","code":"37","siruta":"34155","county_id":6},{"id":487,"name":"PETRU RARE\u015e","code":"38","siruta":"34173","county_id":6},{"id":512,"name":"POIANA ILVEI","code":"39","siruta":"179720","county_id":6},{"id":488,"name":"PRUNDU B\u00c2RG\u0102ULUI","code":"40","siruta":"34235","county_id":6},{"id":489,"name":"REBRA","code":"41","siruta":"34262","county_id":6},{"id":490,"name":"REBRI\u015eOARA","code":"42","siruta":"34280","county_id":6},{"id":491,"name":"RODNA","code":"43","siruta":"34333","county_id":6},{"id":492,"name":"ROMULI","code":"44","siruta":"34360","county_id":6},{"id":513,"name":"RUNCU SALVEI","code":"45","siruta":"179944","county_id":6},{"id":493,"name":"SALVA","code":"46","siruta":"34397","county_id":6},{"id":495,"name":"S\u00c2NMIHAIU DE C\u00c2MPIE","code":"47","siruta":"34477","county_id":6},{"id":497,"name":"\u015eAN\u0162","code":"50","siruta":"34618","county_id":6},{"id":498,"name":"\u015eIEU","code":"51","siruta":"34645","county_id":6},{"id":499,"name":"\u015eIEU-M\u0102GHERU\u015e","code":"52","siruta":"34690","county_id":6},{"id":500,"name":"\u015eIEU-ODORHEI","code":"53","siruta":"34770","county_id":6},{"id":501,"name":"\u015eIEU\u0162","code":"54","siruta":"34850","county_id":6},{"id":494,"name":"SILIVA\u015eU DE C\u00c2MPIE","code":"48","siruta":"34422","county_id":6},{"id":502,"name":"\u015eINTEREAG","code":"55","siruta":"34903","county_id":6},{"id":496,"name":"SPERMEZEU","code":"49","siruta":"34547","county_id":6},{"id":506,"name":"T\u00c2RLI\u015eUA","code":"56","siruta":"35152","county_id":6},{"id":503,"name":"TEACA","code":"57","siruta":"34985","county_id":6},{"id":504,"name":"TELCIU","code":"58","siruta":"35054","county_id":6},{"id":505,"name":"TIHA B\u00c2RG\u0102ULUI","code":"59","siruta":"35090","county_id":6},{"id":507,"name":"URIU","code":"60","siruta":"35269","county_id":6},{"id":508,"name":"URMENI\u015e","code":"61","siruta":"35312","county_id":6},{"id":509,"name":"ZAGRA","code":"62","siruta":"35429","county_id":6}]