[{"id":91,"name":"ALMA\u015e","code":"11","siruta":"9743","county_id":2},{"id":92,"name":"APATEU","code":"12","siruta":"9798","county_id":2},{"id":93,"name":"ARCHI\u015e","code":"13","siruta":"9832","county_id":2},{"id":97,"name":"B\u00c2RSA","code":"15","siruta":"10051","county_id":2},{"id":98,"name":"B\u00c2RZAVA","code":"16","siruta":"10104","county_id":2},{"id":94,"name":"BATA","code":"14","siruta":"9887","county_id":2},{"id":95,"name":"BELIU","code":"17","siruta":"9930","county_id":2},{"id":96,"name":"BIRCHI\u015e","code":"18","siruta":"10006","county_id":2},{"id":99,"name":"BOCSIG","code":"19","siruta":"10195","county_id":2},{"id":100,"name":"BRAZII","code":"20","siruta":"10239","county_id":2},{"id":101,"name":"BUTENI","code":"21","siruta":"10293","county_id":2},{"id":102,"name":"C\u0102RAND","code":"22","siruta":"10346","county_id":2},{"id":103,"name":"CERMEI","code":"23","siruta":"10373","county_id":2},{"id":104,"name":"CHISINDIA","code":"24","siruta":"10417","county_id":2},{"id":105,"name":"CONOP","code":"25","siruta":"10453","county_id":2},{"id":106,"name":"COV\u0102SIN\u0162","code":"26","siruta":"10514","county_id":2},{"id":107,"name":"CRAIVA","code":"27","siruta":"10532","county_id":2},{"id":108,"name":"DEZNA","code":"28","siruta":"10649","county_id":2},{"id":109,"name":"DIECI","code":"29","siruta":"10701","county_id":2},{"id":154,"name":"DOROBAN\u0162I","code":"30","siruta":"12912","county_id":2},{"id":80,"name":"F\u00c2NT\u00c2NELE","code":"31","siruta":"9280","county_id":2},{"id":111,"name":"FELNAC","code":"32","siruta":"10827","county_id":2},{"id":155,"name":"FRUMU\u015eENI","code":"33","siruta":"12920","county_id":2},{"id":112,"name":"GHIOROC","code":"34","siruta":"10872","county_id":2},{"id":113,"name":"GR\u0102NICERI","code":"35","siruta":"10916","county_id":2},{"id":114,"name":"GURAHON\u0162","code":"36","siruta":"10943","county_id":2},{"id":116,"name":"H\u0102LM\u0102GEL","code":"38","siruta":"11174","county_id":2},{"id":115,"name":"H\u0102LMAGIU","code":"37","siruta":"11058","county_id":2},{"id":117,"name":"H\u0102\u015eMA\u015e","code":"39","siruta":"11236","county_id":2},{"id":118,"name":"IGNE\u015eTI","code":"40","siruta":"11307","county_id":2},{"id":119,"name":"IRATO\u015eU","code":"41","siruta":"11352","county_id":2},{"id":81,"name":"LIVADA","code":"42","siruta":"9333","county_id":2},{"id":120,"name":"MACEA","code":"43","siruta":"11398","county_id":2},{"id":121,"name":"MI\u015eCA","code":"44","siruta":"11423","county_id":2},{"id":122,"name":"MONEASA","code":"45","siruta":"11478","county_id":2},{"id":79,"name":"MUNICIPIUL ARAD","code":"1","siruta":"9262","county_id":2},{"id":123,"name":"OLARI","code":"46","siruta":"11502","county_id":2},{"id":84,"name":"ORA\u015e CHI\u015eINEU-CRI\u015e","code":"2","siruta":"9459","county_id":2},{"id":85,"name":"ORA\u015e CURTICI","code":"3","siruta":"9495","county_id":2},{"id":86,"name":"ORA\u015e INEU","code":"4","siruta":"9538","county_id":2},{"id":87,"name":"ORA\u015e LIPOVA","code":"5","siruta":"9574","county_id":2},{"id":88,"name":"ORA\u015e N\u0102DLAC","code":"6","siruta":"9627","county_id":2},{"id":89,"name":"ORA\u015e P\u00c2NCOTA","code":"7","siruta":"9654","county_id":2},{"id":125,"name":"ORA\u015e PECICA","code":"8","siruta":"11584","county_id":2},{"id":135,"name":"ORA\u015e S\u00c2NTANA","code":"9","siruta":"12091","county_id":2},{"id":90,"name":"ORA\u015e SEBI\u015e","code":"10","siruta":"9690","county_id":2},{"id":124,"name":"P\u0102ULI\u015e","code":"47","siruta":"11539","county_id":2},{"id":126,"name":"PEREGU MARE","code":"48","siruta":"11637","county_id":2},{"id":127,"name":"PETRI\u015e","code":"49","siruta":"11664","county_id":2},{"id":128,"name":"PILU","code":"50","siruta":"11735","county_id":2},{"id":129,"name":"PLE\u015eCU\u0162A","code":"51","siruta":"11762","county_id":2},{"id":137,"name":"\u015eAGU","code":"58","siruta":"12144","county_id":2},{"id":130,"name":"S\u0102V\u00c2R\u015eIN","code":"52","siruta":"11842","county_id":2},{"id":131,"name":"SECUSIGIU","code":"53","siruta":"11940","county_id":2},{"id":138,"name":"\u015eEITIN","code":"59","siruta":"12206","county_id":2},{"id":132,"name":"SELEU\u015e","code":"54","siruta":"11995","county_id":2},{"id":133,"name":"SEMLAC","code":"55","siruta":"12037","county_id":2},{"id":139,"name":"\u015eEPREU\u015e","code":"60","siruta":"12224","county_id":2},{"id":140,"name":"\u015eICULA","code":"61","siruta":"12242","county_id":2},{"id":141,"name":"\u015eILINDIA","code":"62","siruta":"12288","county_id":2},{"id":142,"name":"\u015eIMAND","code":"63","siruta":"12340","county_id":2},{"id":134,"name":"SINTEA MARE","code":"56","siruta":"12055","county_id":2},{"id":143,"name":"\u015eIRIA","code":"64","siruta":"12368","county_id":2},{"id":144,"name":"\u015eI\u015eTAROV\u0102\u0162","code":"65","siruta":"12402","county_id":2},{"id":136,"name":"SOCODOR","code":"57","siruta":"12126","county_id":2},{"id":82,"name":"\u015eOFRONEA","code":"66","siruta":"9360","county_id":2},{"id":146,"name":"T\u00c2RNOVA","code":"68","siruta":"12509","county_id":2},{"id":145,"name":"TAU\u0162","code":"67","siruta":"12457","county_id":2},{"id":110,"name":"USUS\u0102U","code":"69","siruta":"10765","county_id":2},{"id":147,"name":"V\u0102R\u0102DIA DE MURE\u015e","code":"70","siruta":"12572","county_id":2},{"id":149,"name":"V\u00c2RFURILE","code":"71","siruta":"12689","county_id":2},{"id":148,"name":"VINGA","code":"72","siruta":"12643","county_id":2},{"id":83,"name":"VLADIMIRESCU","code":"73","siruta":"9397","county_id":2},{"id":150,"name":"Z\u0102BRANI","code":"74","siruta":"12778","county_id":2},{"id":156,"name":"Z\u0102D\u0102RENI","code":"75","siruta":"12938","county_id":2},{"id":151,"name":"Z\u0102RAND","code":"76","siruta":"12812","county_id":2},{"id":152,"name":"ZERIND","code":"77","siruta":"12849","county_id":2},{"id":153,"name":"ZIMANDU NOU","code":"78","siruta":"12876","county_id":2}]